flask_http_response/__init__.py
flask_http_response/main.py
flask_http_response-0.0.1.0.dist-info/LICENSE
flask_http_response-0.0.1.0.dist-info/METADATA
flask_http_response-0.0.1.0.dist-info/WHEEL
flask_http_response-0.0.1.0.dist-info/entry_points.txt
flask_http_response-0.0.1.0.dist-info/top_level.txt
flask_http_response-0.0.1.0.dist-info/RECORD
