Metadata-Version: 2.1
Name: flask-http-response
Version: 0.0.1.0
Summary: UNKNOWN
Home-page: https://github.com/raisulru/flask-http-response.git
Author: Raisul Islam
Author-email: raisulru10@gmail.com
License: License :: OSI Approved :: MIT License
Platform: UNKNOWN
Classifier: Programming Language :: Python
Requires-Python: >=3.6
